{
  "Width": 200,
  "Height": 200,
  "levelNumber": 0,
  "levelChapter": 0,
  "walls": [
    {
      "Point1": {
        "XPos": 500,
        "YPos": -50
      },
      "Point2": {
        "XPos": 500,
        "YPos": 0
      },
      "Type": 0,
      "Texture1": "/resources/Level_Strip/PlainGreen.png",
      "Texture2": "/resources/Level_Strip/PlainGreen.png"
    },
    {
      "Point1": {
        "XPos": 450,
        "YPos": 200
      },
      "Point2": {
        "XPos": 400,
        "YPos": 100
      },
      "Type": 0,
      "Texture1": "/resources/Level_Strip/PlainGreen.png",
      "Texture2": "/resources/Level_Strip/PlainGreen.png"
    }
  ],
  "props": [
    {
      "Rotation": 45,
      "Coordinates": {
        "XPos": -25,
        "YPos": -500
      },
      "PropTexture": "/resources/Level_Strip/box.png"
    },
    {
      "Rotation": 45,
      "Coordinates": {
        "XPos": 500,
        "YPos": -50
      },
      "PropTexture": "/resources/Level_Strip/toilet.png"
    }
  ],
  "npcs": [],
  "pathPoints": [],
  "miscs": [],
  "floors": null
}